MANIFEST.in
README
setup.py
Petrified.egg-info/PKG-INFO
Petrified.egg-info/SOURCES.txt
Petrified.egg-info/dependency_links.txt
Petrified.egg-info/not-zip-safe
Petrified.egg-info/requires.txt
Petrified.egg-info/top_level.txt
petrified/__init__.py
petrified/datatype.py
petrified/form.py
petrified/lib.py
petrified/renderers.py
petrified/validator.py
petrified/widget.py
petrified/datatypes/__init__.py
petrified/templates/checkbox.html
petrified/templates/form.html
petrified/templates/hidden.html
petrified/templates/lib.html
petrified/templates/password.html
petrified/templates/radiobox.html
petrified/templates/selectbox.html
petrified/templates/submitbutton.html
petrified/templates/text.html
petrified/templates/textarea.html
petrified/templates/textfield.html
petrified/templates/widget.html
petrified/validators/__init__.py
petrified/widgets/__init__.py