Metadata-Version: 1.0
Name: Petrified
Version: 0.0
Summary: Scary form toolkit of a solidifying nature.
Home-page: UNKNOWN
Author: Derek McTavish Mounce
Author-email: derek@hazelspace.com
License: MIT
Platform: UNKNOWN
